lvpocket/__init__.py
lvpocket/model/LV_former.py
lvpocket/model/__init__.py
lvpocket/model/data.py
LVPocket-0.2.4.dist-info/LICENSE
LVPocket-0.2.4.dist-info/METADATA
LVPocket-0.2.4.dist-info/WHEEL
LVPocket-0.2.4.dist-info/top_level.txt
LVPocket-0.2.4.dist-info/RECORD
